{"pageContext":{"jsonName":"en-videos-207","internalComponentName":"ComponentEnVideos","path":"/en/videos/","component":"/home/ubuntu/PetProjects/caddysmellsliketrees.ru/src/pages/videos.en.tsx","componentChunkName":"component---src-pages-videos-en-tsx","context":{"slug":"/en/videos/","langKey":"en"},"updatedAt":1530700635746,"pluginCreator___NODE":"Plugin gatsby-plugin-i18n","pluginCreatorId":"Plugin gatsby-plugin-i18n","componentPath":"/home/ubuntu/PetProjects/caddysmellsliketrees.ru/src/pages/videos.en.tsx","slug":"/en/videos/","langKey":"en"}}